myrage/__init__.py
myrage/geoip
myrage/geoip6
myrage/myrage.py
myrage-0.0.20.dist-info/METADATA
myrage-0.0.20.dist-info/WHEEL
myrage-0.0.20.dist-info/top_level.txt
myrage-0.0.20.dist-info/RECORD
