Metadata-Version: 2.4
Name: myrage
Version: 0.0.20
Summary: A simple class to instanciate a tor process and run http requests behind it
Author: Cyril Quijoux
Keywords: tor,requests,http,https
Requires-Dist: requests
Requires-Dist: requests[socks]
Requires-Dist: stem
Requires-Dist: psutil
Requires-Dist: decolog
